whTool
