Metadata-Version: 1.0
Name: whTool
Version: 0.0.4
Summary: a library for wh Developer
Home-page: https://gitlab.enncloud.cn/wenhaoc/whTool.git
Author: wenhaoc
Author-email: wenhaoc@enn.cn
License: MIT License
Keywords: wh
Platform: any
